{
  "keyword": "Explainability",
  "limit_per_pattern": 50,
  "num_hits": 23,
  "hits": [
    {
      "relation": {
        "source": {
          "label": "explainability",
          "id": "4:d4d30991-8f5b-4b2f-87f2-35ae5b6aebf6:44"
        },
        "target": {
          "label": "fairness",
          "id": "4:d4d30991-8f5b-4b2f-87f2-35ae5b6aebf6:26"
        },
        "edge": {
          "label": "is used to help with",
          "properties": {
            "sentence": "Explainability is used to help with robustness or fairness.",
            "last_updated_at": "2026-02-11T17:09:09.834000000+00:00",
            "created_at": "2026-02-11T14:12:38.469789+00:00",
            "label": "is used to help with",
            "source": "data/SDS/Unifying_VXAI_pages_01_to_08.pdf"
          }
        }
      },
      "match_pattern": "source_label"
    },
    {
      "relation": {
        "source": {
          "label": "explainability",
          "id": "4:d4d30991-8f5b-4b2f-87f2-35ae5b6aebf6:44"
        },
        "target": {
          "label": "requirement",
          "id": "4:d4d30991-8f5b-4b2f-87f2-35ae5b6aebf6:59"
        },
        "edge": {
          "label": "is",
          "properties": {
            "sentence": "explainability is requirement",
            "type": "is",
            "label": "is"
          }
        }
      },
      "match_pattern": "source_label"
    },
    {
      "relation": {
        "source": {
          "label": "explainability",
          "id": "4:d4d30991-8f5b-4b2f-87f2-35ae5b6aebf6:44"
        },
        "target": {
          "label": "transparency",
          "id": "4:d4d30991-8f5b-4b2f-87f2-35ae5b6aebf6:73"
        },
        "edge": {
          "label": "is_dimension_of",
          "properties": {
            "sentence": "explainability is_dimension_of transparency",
            "type": "is_dimension_of",
            "label": "is_dimension_of"
          }
        }
      },
      "match_pattern": "source_label"
    },
    {
      "relation": {
        "source": {
          "label": "explainability",
          "id": "4:d4d30991-8f5b-4b2f-87f2-35ae5b6aebf6:44"
        },
        "target": {
          "label": "accuracy",
          "id": "4:d4d30991-8f5b-4b2f-87f2-35ae5b6aebf6:74"
        },
        "edge": {
          "label": "can_affect",
          "properties": {
            "sentence": "explainability can_affect accuracy",
            "type": "can_affect",
            "label": "can_affect"
          }
        }
      },
      "match_pattern": "source_label"
    },
    {
      "relation": {
        "source": {
          "label": "explainability",
          "id": "4:d4d30991-8f5b-4b2f-87f2-35ae5b6aebf6:44"
        },
        "target": {
          "label": "technical_robustness",
          "id": "4:d4d30991-8f5b-4b2f-87f2-35ae5b6aebf6:75"
        },
        "edge": {
          "label": "helps",
          "properties": {
            "sentence": "explainability helps technical_robustness",
            "type": "helps",
            "label": "helps"
          }
        }
      },
      "match_pattern": "source_label"
    },
    {
      "relation": {
        "source": {
          "label": "explainability",
          "id": "4:d4d30991-8f5b-4b2f-87f2-35ae5b6aebf6:44"
        },
        "target": {
          "label": "robustness",
          "id": "4:d4d30991-8f5b-4b2f-87f2-35ae5b6aebf6:166"
        },
        "edge": {
          "label": "is used to help with",
          "properties": {
            "sentence": "Explainability is used to help with robustness or fairness.",
            "last_updated_at": "2026-02-11T17:09:09.416000000+00:00",
            "created_at": "2026-02-11T14:12:38.343179+00:00",
            "label": "is used to help with",
            "source": "data/SDS/Unifying_VXAI_pages_01_to_08.pdf"
          }
        }
      },
      "match_pattern": "source_label"
    },
    {
      "relation": {
        "source": {
          "label": "explainability",
          "id": "4:d4d30991-8f5b-4b2f-87f2-35ae5b6aebf6:44"
        },
        "target": {
          "label": "trustworthiness",
          "id": "4:d4d30991-8f5b-4b2f-87f2-35ae5b6aebf6:168"
        },
        "edge": {
          "label": "is used to help with other dimensions of",
          "properties": {
            "sentence": "Explainability is used to help with other dimensions of trustworthiness.",
            "last_updated_at": "2026-02-11T17:09:09.808000000+00:00",
            "created_at": "2026-02-11T17:09:09.801354+00:00",
            "label": "is used to help with other dimensions of",
            "source": "data/SDS/Unifying_VXAI_pages_01_to_08.pdf"
          }
        }
      },
      "match_pattern": "source_label"
    },
    {
      "relation": {
        "source": {
          "label": "explainability",
          "id": "4:d4d30991-8f5b-4b2f-87f2-35ae5b6aebf6:44"
        },
        "target": {
          "label": "privacy",
          "id": "4:d4d30991-8f5b-4b2f-87f2-35ae5b6aebf6:169"
        },
        "edge": {
          "label": "is used to help with",
          "properties": {
            "sentence": "Explainability is used to help with privacy, robustness, or fairness.",
            "last_updated_at": "2026-02-11T17:09:09.265000000+00:00",
            "created_at": "2026-02-11T14:12:38.763120+00:00",
            "label": "is used to help with",
            "source": "data/SDS/Unifying_VXAI_pages_01_to_08.pdf"
          }
        }
      },
      "match_pattern": "source_label"
    },
    {
      "relation": {
        "source": {
          "label": "explainability",
          "id": "4:d4d30991-8f5b-4b2f-87f2-35ae5b6aebf6:44"
        },
        "target": {
          "label": "other dimensions of trustworthiness",
          "id": "4:d4d30991-8f5b-4b2f-87f2-35ae5b6aebf6:172"
        },
        "edge": {
          "label": "is used to help with",
          "properties": {
            "sentence": "Explainability is used to help with other dimensions of trustworthiness.",
            "last_updated_at": "2026-02-11T14:12:39.050000000+00:00",
            "created_at": "2026-02-11T14:12:39.042795+00:00",
            "label": "is used to help with",
            "source": "data/SDS/Unifying_VXAI_pages_01_to_08.pdf"
          }
        }
      },
      "match_pattern": "source_label"
    },
    {
      "relation": {
        "source": {
          "label": "explainability",
          "id": "4:d4d30991-8f5b-4b2f-87f2-35ae5b6aebf6:44"
        },
        "target": {
          "label": "explanations",
          "id": "4:d4d30991-8f5b-4b2f-87f2-35ae5b6aebf6:184"
        },
        "edge": {
          "label": "are used inconsistently",
          "properties": {
            "sentence": "Terms such as interpretability, comprehensibility, understandability, transparency, and explainability are used inconsistently.",
            "last_updated_at": "2026-02-11T17:09:11.190000000+00:00",
            "created_at": "2026-02-11T17:09:11.183818+00:00",
            "label": "are used inconsistently",
            "source": "data/SDS/Unifying_VXAI_pages_01_to_08.pdf"
          }
        }
      },
      "match_pattern": "source_label"
    },
    {
      "relation": {
        "source": {
          "label": "explainability",
          "id": "4:d4d30991-8f5b-4b2f-87f2-35ae5b6aebf6:44"
        },
        "target": {
          "label": "properties",
          "id": "4:d4d30991-8f5b-4b2f-87f2-35ae5b6aebf6:187"
        },
        "edge": {
          "label": "are excluded",
          "properties": {
            "sentence": "Properties beyond explainability are excluded.",
            "last_updated_at": "2026-02-11T17:09:09.021000000+00:00",
            "created_at": "2026-02-11T17:09:08.948429+00:00",
            "label": "are excluded",
            "source": "data/SDS/Unifying_VXAI_pages_01_to_08.pdf"
          }
        }
      },
      "match_pattern": "source_label"
    },
    {
      "relation": {
        "source": {
          "label": "Explainability",
          "id": "4:d4d30991-8f5b-4b2f-87f2-35ae5b6aebf6:90"
        },
        "target": {
          "label": "property",
          "id": "4:d4d30991-8f5b-4b2f-87f2-35ae5b6aebf6:91"
        },
        "edge": {
          "label": "is",
          "properties": {
            "sentence": "Explainability is a property of AI model.",
            "page_number": 4,
            "original_sentence": "Explainability is often understood as a property of an →AI model or →AI system that is\nmeasured locally and independently of the system design (\"post-hoc\").",
            "last_updated_at": "2025-11-27T17:16:24.714000000+00:00",
            "created_at": "2025-11-27T17:16:24.617344+00:00",
            "label": "is",
            "source": "20241015_MISSION_KI_Glossar_v1.0 en"
          }
        }
      },
      "match_pattern": "source_label"
    },
    {
      "relation": {
        "source": {
          "label": "Explainability",
          "id": "4:d4d30991-8f5b-4b2f-87f2-35ae5b6aebf6:90"
        },
        "target": {
          "label": "AI model",
          "id": "4:d4d30991-8f5b-4b2f-87f2-35ae5b6aebf6:92"
        },
        "edge": {
          "label": "is property of",
          "properties": {
            "sentence": "Explainability is property of AI model or AI system",
            "page_number": 4,
            "original_sentence": "Explainability is often understood as a property of an →AI model or →AI system that is\nmeasured locally and independently of the system design (\"post-hoc\").",
            "last_updated_at": "2025-11-27T18:23:41.977000000+00:00",
            "created_at": "2025-11-27T18:23:41.883759+00:00",
            "label": "is property of",
            "source": "20241015_MISSION_KI_Glossar_v1.0 en"
          }
        }
      },
      "match_pattern": "source_label"
    },
    {
      "relation": {
        "source": {
          "label": "Explainability",
          "id": "4:d4d30991-8f5b-4b2f-87f2-35ae5b6aebf6:90"
        },
        "target": {
          "label": "system design",
          "id": "4:d4d30991-8f5b-4b2f-87f2-35ae5b6aebf6:93"
        },
        "edge": {
          "label": "is measured independently of",
          "properties": {
            "sentence": "Explainability is measured independently of system design (post-hoc)",
            "page_number": 4,
            "original_sentence": "Explainability is often understood as a property of an →AI model or →AI system that is\nmeasured locally and independently of the system design (\"post-hoc\").",
            "last_updated_at": "2025-11-27T18:25:39.565000000+00:00",
            "created_at": "2025-11-27T18:25:39.479189+00:00",
            "label": "is measured independently of",
            "source": "20241015_MISSION_KI_Glossar_v1.0 en"
          }
        }
      },
      "match_pattern": "source_label"
    },
    {
      "relation": {
        "source": {
          "label": "explanation_robustness",
          "id": "4:d4d30991-8f5b-4b2f-87f2-35ae5b6aebf6:45"
        },
        "target": {
          "label": "explainability",
          "id": "4:d4d30991-8f5b-4b2f-87f2-35ae5b6aebf6:44"
        },
        "edge": {
          "label": "is_subclass_of",
          "properties": {
            "sentence": "explanation_robustness is_subclass_of explainability",
            "type": "is_subclass_of",
            "label": "is_subclass_of"
          }
        }
      },
      "match_pattern": "target_label"
    },
    {
      "relation": {
        "source": {
          "label": "interpretability",
          "id": "4:d4d30991-8f5b-4b2f-87f2-35ae5b6aebf6:174"
        },
        "target": {
          "label": "explainability",
          "id": "4:d4d30991-8f5b-4b2f-87f2-35ae5b6aebf6:44"
        },
        "edge": {
          "label": "is a major component of",
          "properties": {
            "sentence": "Interpretability and Fidelity are major components of explainability.",
            "last_updated_at": "2026-02-11T14:12:39.280000000+00:00",
            "created_at": "2026-02-11T14:12:39.100088+00:00",
            "label": "is a major component of",
            "source": "data/SDS/Unifying_VXAI_pages_01_to_08.pdf"
          }
        }
      },
      "match_pattern": "target_label"
    },
    {
      "relation": {
        "source": {
          "label": "interpretability",
          "id": "4:d4d30991-8f5b-4b2f-87f2-35ae5b6aebf6:174"
        },
        "target": {
          "label": "explainability",
          "id": "4:d4d30991-8f5b-4b2f-87f2-35ae5b6aebf6:44"
        },
        "edge": {
          "label": "are major components of",
          "properties": {
            "sentence": "Interpretability and Fidelity are major components of explainability.",
            "last_updated_at": "2026-02-11T17:09:09.590000000+00:00",
            "created_at": "2026-02-11T17:09:09.582509+00:00",
            "label": "are major components of",
            "source": "data/SDS/Unifying_VXAI_pages_01_to_08.pdf"
          }
        }
      },
      "match_pattern": "target_label"
    },
    {
      "relation": {
        "source": {
          "label": "fidelity",
          "id": "4:d4d30991-8f5b-4b2f-87f2-35ae5b6aebf6:175"
        },
        "target": {
          "label": "explainability",
          "id": "4:d4d30991-8f5b-4b2f-87f2-35ae5b6aebf6:44"
        },
        "edge": {
          "label": "is a major component of",
          "properties": {
            "sentence": "Interpretability and Fidelity are major components of explainability.",
            "last_updated_at": "2026-02-11T14:12:39.336000000+00:00",
            "created_at": "2026-02-11T14:12:39.125987+00:00",
            "label": "is a major component of",
            "source": "data/SDS/Unifying_VXAI_pages_01_to_08.pdf"
          }
        }
      },
      "match_pattern": "target_label"
    },
    {
      "relation": {
        "source": {
          "label": "fidelity",
          "id": "4:d4d30991-8f5b-4b2f-87f2-35ae5b6aebf6:175"
        },
        "target": {
          "label": "explainability",
          "id": "4:d4d30991-8f5b-4b2f-87f2-35ae5b6aebf6:44"
        },
        "edge": {
          "label": "are major components of",
          "properties": {
            "sentence": "Interpretability and Fidelity are major components of explainability.",
            "last_updated_at": "2026-02-11T17:09:09.620000000+00:00",
            "created_at": "2026-02-11T17:09:09.612483+00:00",
            "label": "are major components of",
            "source": "data/SDS/Unifying_VXAI_pages_01_to_08.pdf"
          }
        }
      },
      "match_pattern": "target_label"
    },
    {
      "relation": {
        "source": {
          "label": "explanations",
          "id": "4:d4d30991-8f5b-4b2f-87f2-35ae5b6aebf6:184"
        },
        "target": {
          "label": "explainability",
          "id": "4:d4d30991-8f5b-4b2f-87f2-35ae5b6aebf6:44"
        },
        "edge": {
          "label": "is assessed to be achieved",
          "properties": {
            "sentence": "A central motivation behind developing comprehensive and unified evaluation standards is to enable the comparison of explanations and assess whether explainability is achieved.",
            "last_updated_at": "2026-02-11T14:12:40.081000000+00:00",
            "created_at": "2026-02-11T14:12:40.074094+00:00",
            "label": "is assessed to be achieved",
            "source": "data/SDS/Unifying_VXAI_pages_01_to_08.pdf"
          }
        }
      },
      "match_pattern": "target_label"
    },
    {
      "relation": {
        "source": {
          "label": "explanations",
          "id": "4:d4d30991-8f5b-4b2f-87f2-35ae5b6aebf6:184"
        },
        "target": {
          "label": "explainability",
          "id": "4:d4d30991-8f5b-4b2f-87f2-35ae5b6aebf6:44"
        },
        "edge": {
          "label": "are assessed to be achieved",
          "properties": {
            "sentence": "A central motivation behind developing comprehensive and unified evaluation standards is to enable the comparison of explanations and assess whether explainability is achieved.",
            "last_updated_at": "2026-02-11T17:09:09.559000000+00:00",
            "created_at": "2026-02-11T17:09:09.551439+00:00",
            "label": "are assessed to be achieved",
            "source": "data/SDS/Unifying_VXAI_pages_01_to_08.pdf"
          }
        }
      },
      "match_pattern": "target_label"
    },
    {
      "relation": {
        "source": {
          "label": "properties",
          "id": "4:d4d30991-8f5b-4b2f-87f2-35ae5b6aebf6:187"
        },
        "target": {
          "label": "explainability",
          "id": "4:d4d30991-8f5b-4b2f-87f2-35ae5b6aebf6:44"
        },
        "edge": {
          "label": "are excluded beyond",
          "properties": {
            "sentence": "Properties beyond explainability are excluded.",
            "last_updated_at": "2026-02-11T14:12:39.898000000+00:00",
            "created_at": "2026-02-11T14:12:39.890959+00:00",
            "label": "are excluded beyond",
            "source": "data/SDS/Unifying_VXAI_pages_01_to_08.pdf"
          }
        }
      },
      "match_pattern": "target_label"
    },
    {
      "relation": {
        "source": {
          "label": "interpretability and fidelity",
          "id": "4:d4d30991-8f5b-4b2f-87f2-35ae5b6aebf6:214"
        },
        "target": {
          "label": "explainability",
          "id": "4:d4d30991-8f5b-4b2f-87f2-35ae5b6aebf6:44"
        },
        "edge": {
          "label": "are major components of",
          "properties": {
            "sentence": "Interpretability and Fidelity are major components of explainability.",
            "last_updated_at": "2026-02-11T17:09:09.777000000+00:00",
            "created_at": "2026-02-11T17:09:09.770395+00:00",
            "label": "are major components of",
            "source": "data/SDS/Unifying_VXAI_pages_01_to_08.pdf"
          }
        }
      },
      "match_pattern": "target_label"
    }
  ],
  "created_at": "20260224_151509Z"
}